{"updatedAt": "2026-06-07T14:28:03.331744", "id": "89", "players": [{"id": "107775", "name": "Frederik Rönnow", "position": "Goalkeeper", "dateOfBirth": "1992-04-08", "age": 33, "nationality": ["Denmark"], "height": 188, "foot": "right", "joinedOn": "2021-07-20", "signedFrom": "Eintracht Frankfurt", "marketValue": 2000000, "status": "Adductor injury - Return expected on 30/06/2026"}, {"id": "386685", "name": "Matheo Raab", "position": "Goalkeeper", "dateOfBirth": "1998-12-18", "age": 27, "nationality": ["Germany"], "height": 186, "foot": "right", "joinedOn": "2025-11-07", "signedFrom": "Hamburger SV", "marketValue": 600000, "status": "Hand injury - Return unknown"}, {"id": "161057", "name": "Carl Klaus", "position": "Goalkeeper", "dateOfBirth": "1994-01-16", "age": 32, "nationality": ["Germany"], "height": 189, "foot": "right", "joinedOn": "2024-07-28", "signedFrom": "1.FC Nuremberg", "marketValue": 350000}, {"id": "597432", "name": "Leopold Querfeld", "position": "Centre-Back", "dateOfBirth": "2003-12-20", "age": 22, "nationality": ["Austria"], "height": 190, "foot": "right", "joinedOn": "2024-01-07", "signedFrom": "Rapid Vienna", "marketValue": 20000000}, {"id": "387047", "name": "Danilho Doekhi", "position": "Centre-Back", "dateOfBirth": "1998-06-30", "age": 27, "nationality": ["Netherlands", "Suriname"], "height": 190, "foot": "right", "joinedOn": "2022-01-07", "signedFrom": "Vitesse Arnhem", "contract": "2026-06-30", "marketValue": 13000000}, {"id": "357156", "name": "Diogo Leite", "position": "Centre-Back", "dateOfBirth": "1999-01-23", "age": 27, "nationality": ["Portugal"], "height": 190, "foot": "left", "joinedOn": "2023-01-07", "signedFrom": "FC Porto", "contract": "2026-06-30", "marketValue": 12000000}, {"id": "371141", "name": "Stanley Nsoki", "position": "Centre-Back", "dateOfBirth": "1999-09-04", "age": 27, "nationality": ["France", "DR Congo"], "height": 184, "foot": "left", "joinedOn": "2025-07-24", "signedFrom": "TSG 1899 Hoffenheim", "contract": "2026-06-30", "marketValue": 2000000}, {"id": "798043", "name": "Tom Rothe", "position": "Left-Back", "dateOfBirth": "2004-10-29", "age": 21, "nationality": ["Germany"], "height": 193, "foot": "left", "joinedOn": "2024-07-08", "signedFrom": "Borussia Dortmund", "marketValue": 10000000}, {"id": "391780", "name": "Derrick Köhn", "position": "Left-Back", "dateOfBirth": "1999-04-02", "age": 27, "nationality": ["Ghana", "Germany"], "height": 180, "foot": "left", "joinedOn": "2025-08-19", "signedFrom": "Galatasaray", "contract": "2029-06-30", "marketValue": 4000000}, {"id": "1027870", "name": "Andrik Markgraf", "position": "Left-Back", "dateOfBirth": "2006-07-03", "age": 20, "nationality": ["Germany"], "height": 172, "foot": "left", "joinedOn": "2025-01-07", "signedFrom": "1.FC Union Berlin U19", "marketValue": 300000}, {"id": "362977", "name": "Josip Juranovic", "position": "Right-Back", "dateOfBirth": "1995-08-16", "age": 30, "nationality": ["Croatia"], "height": 173, "foot": "right", "joinedOn": "2023-01-22", "signedFrom": ": Ablöse €8.55m", "marketValue": 2000000}, {"id": "75921", "name": "Christopher Trimmel", "position": "Right-Back", "dateOfBirth": "1987-02-24", "age": 39, "nationality": ["Austria"], "height": 189, "foot": "right", "joinedOn": "2014-01-07", "signedFrom": "Rapid Vienna", "contract": "2027-06-30", "marketValue": 600000, "status": "Team captain"}, {"id": "692737", "name": "Aljoscha Kemlein", "position": "Defensive Midfield", "dateOfBirth": "2004-02-08", "age": 21, "nationality": ["Germany"], "height": 188, "foot": "right", "joinedOn": "2023-01-07", "signedFrom": "1.FC Union Berlin U19", "contract": "2029-06-30", "marketValue": 12000000}, {"id": "124410", "name": "Rani Khedira", "position": "Defensive Midfield", "dateOfBirth": "1994-01-27", "age": 32, "nationality": ["Tunisia", "Germany"], "height": 188, "foot": "right", "joinedOn": "2021-01-07", "signedFrom": "FC Augsburg", "contract": "2026-06-30", "marketValue": 2000000}, {"id": "454863", "name": "András Schäfer", "position": "Central Midfield", "dateOfBirth": "1999-04-13", "age": 27, "nationality": ["Hungary"], "height": 178, "foot": "right", "joinedOn": "2022-01-21", "signedFrom": "DAC Dunajska Streda", "contract": "2027-06-30", "marketValue": 4500000}, {"id": "337333", "name": "Alex Král", "position": "Central Midfield", "dateOfBirth": "1998-05-19", "age": 28, "nationality": ["Czech Republic"], "height": 186, "foot": "right", "joinedOn": "2024-01-07", "signedFrom": "Spartak Moscow", "contract": "2026-06-30", "marketValue": 2500000}, {"id": "177779", "name": "Janik Haberer", "position": "Central Midfield", "dateOfBirth": "1994-02-04", "age": 32, "nationality": ["Germany"], "height": 187, "foot": "right", "joinedOn": "2022-01-07", "signedFrom": "SC Freiburg", "contract": "2027-06-30", "marketValue": 2000000}, {"id": "270393", "name": "Robert Skov", "position": "Left Midfield", "dateOfBirth": "1996-05-20", "age": 30, "nationality": ["Denmark"], "height": 185, "foot": "left", "joinedOn": "2024-04-09", "signedFrom": "Without Club", "marketValue": 2000000}, {"id": "297583", "name": "Woo-yeong Jeong", "position": "Attacking Midfield", "dateOfBirth": "1999-09-20", "age": 26, "nationality": ["Korea, South"], "height": 179, "foot": "right", "joinedOn": "2025-01-07", "signedFrom": "VfB Stuttgart", "marketValue": 3500000}, {"id": "519872", "name": "Livan Burcu", "position": "Left Winger", "dateOfBirth": "2004-09-28", "age": 21, "nationality": ["Türkiye", "Germany"], "height": 180, "foot": "right", "joinedOn": "2024-07-20", "signedFrom": "SV Sandhausen", "marketValue": 4000000}, {"id": "745075", "name": "David Preu", "position": "Left Winger", "dateOfBirth": "2004-10-26", "age": 21, "nationality": ["Germany"], "height": 172, "foot": "right", "joinedOn": "2023-01-07", "signedFrom": "1.FC Union Berlin U19", "marketValue": 400000}, {"id": "1035765", "name": "Ilyas Ansah", "position": "Centre-Forward", "dateOfBirth": "2004-08-11", "age": 21, "nationality": ["Germany", "Ghana"], "height": 197, "foot": "right", "joinedOn": "2025-01-07", "signedFrom": "SC Paderborn 07", "marketValue": 12000000}, {"id": "583699", "name": "Andrej Ilic", "position": "Centre-Forward", "dateOfBirth": "2000-03-04", "age": 26, "nationality": ["Serbia"], "height": 189, "foot": "right", "joinedOn": "2025-01-07", "signedFrom": "LOSC Lille", "contract": "2027-06-30", "marketValue": 9000000}, {"id": "341317", "name": "Oliver Burke", "position": "Centre-Forward", "dateOfBirth": "1997-07-04", "age": 29, "nationality": ["Scotland"], "height": 188, "foot": "right", "joinedOn": "2025-01-07", "signedFrom": "SV Werder Bremen", "contract": "2029-06-30", "marketValue": 3000000}, {"id": "287920", "name": "Tim Skarke", "position": "Centre-Forward", "dateOfBirth": "1996-07-09", "age": 29, "nationality": ["Germany"], "height": 181, "foot": "right", "joinedOn": "2022-01-07", "signedFrom": "SV Darmstadt 98", "marketValue": 1500000}, {"id": "1045446", "name": "Dmytro Bogdanov", "position": "Centre-Forward", "dateOfBirth": "2007-06-03", "age": 19, "nationality": ["Ukraine"], "height": 188, "foot": "right", "joinedOn": "2025-08-13", "signedFrom": "SG Dynamo Dresden", "contract": "2029-06-30", "marketValue": 800000}]}