{"updatedAt": "2026-06-07T14:26:14.086339", "id": "331", "players": [{"id": "248738", "name": "Sergio Herrera", "position": "Goalkeeper", "dateOfBirth": "1993-05-06", "age": 33, "nationality": ["Spain"], "height": 192, "foot": "right", "joinedOn": "2017-12-07", "signedFrom": "SD Huesca", "contract": "2028-06-30", "marketValue": 2800000}, {"id": "118997", "name": "Aitor Fernández", "position": "Goalkeeper", "dateOfBirth": "1991-03-05", "age": 35, "nationality": ["Spain"], "height": 182, "foot": "right", "joinedOn": "2022-02-07", "signedFrom": "Levante UD", "contract": "2027-06-30", "marketValue": 500000}, {"id": "541555", "name": "Enzo Boyomo", "position": "Centre-Back", "dateOfBirth": "2001-07-10", "age": 24, "nationality": ["Cameroon", "France"], "height": 184, "foot": "right", "joinedOn": "2024-08-29", "signedFrom": "Real Valladolid CF", "contract": "2029-06-30", "marketValue": 15000000}, {"id": "555500", "name": "Jorge Herrando", "position": "Centre-Back", "dateOfBirth": "2001-02-28", "age": 25, "nationality": ["Spain"], "height": 192, "foot": "left", "joinedOn": "2023-01-07", "signedFrom": "CA Osasuna Promesas", "contract": "2030-06-30", "marketValue": 3500000}, {"id": "449796", "name": "Alejandro Catena", "position": "Centre-Back", "dateOfBirth": "1994-10-28", "age": 31, "nationality": ["Spain"], "height": 194, "foot": "right", "joinedOn": "2023-01-07", "signedFrom": "Rayo Vallecano", "contract": "2028-06-30", "marketValue": 2600000}, {"id": "658115", "name": "Abel Bretones", "position": "Left-Back", "dateOfBirth": "2000-08-21", "age": 25, "nationality": ["Spain"], "height": 188, "foot": "left", "joinedOn": "2024-05-07", "signedFrom": "Real Oviedo", "contract": "2029-06-30", "marketValue": 3500000}, {"id": "448628", "name": "Javi Galán", "position": "Left-Back", "dateOfBirth": "1994-11-19", "age": 31, "nationality": ["Spain"], "height": 172, "foot": "left", "joinedOn": "2026-01-01", "signedFrom": "Atlético de Madrid", "contract": "2026-06-30", "marketValue": 1800000}, {"id": "169497", "name": "Juan Cruz", "position": "Left-Back", "dateOfBirth": "1992-07-28", "age": 33, "nationality": ["Spain"], "height": 182, "foot": "left", "joinedOn": "2020-08-30", "signedFrom": "Elche CF", "contract": "2026-06-30", "marketValue": 1000000}, {"id": "441170", "name": "Valentin Rosier", "position": "Right-Back", "dateOfBirth": "1996-08-19", "age": 29, "nationality": ["France", "Guadeloupe"], "height": 175, "foot": "right", "joinedOn": "2025-01-07", "signedFrom": "CD Leganés", "contract": "2028-06-30", "marketValue": 3000000}, {"id": "1065442", "name": "Iñigo Arguibide", "position": "Right-Back", "dateOfBirth": "2005-04-19", "age": 21, "nationality": ["Spain"], "height": 178, "foot": "right", "joinedOn": "2026-01-01", "signedFrom": "CA Osasuna Promesas", "contract": "2027-06-30", "marketValue": 800000}, {"id": "213670", "name": "Lucas Torró", "position": "Defensive Midfield", "dateOfBirth": "1994-07-19", "age": 31, "nationality": ["Spain"], "height": 190, "foot": "right", "joinedOn": "2020-04-08", "signedFrom": "Eintracht Frankfurt", "contract": "2027-06-30", "marketValue": 2500000}, {"id": "710677", "name": "Iker Muñoz", "position": "Defensive Midfield", "dateOfBirth": "2002-05-09", "age": 23, "nationality": ["Spain"], "height": 180, "foot": "right", "joinedOn": "2023-01-07", "signedFrom": "CA Osasuna Promesas", "contract": "2030-06-30", "marketValue": 2000000}, {"id": "552425", "name": "Jon Moncayola", "position": "Central Midfield", "dateOfBirth": "1998-05-13", "age": 28, "nationality": ["Spain"], "height": 182, "foot": "right", "joinedOn": "2019-01-07", "signedFrom": "CA Osasuna Promesas", "contract": "2031-06-30", "marketValue": 7000000}, {"id": "1038512", "name": "Asier Osambela", "position": "Central Midfield", "dateOfBirth": "2004-10-30", "age": 21, "nationality": ["Spain"], "height": 186, "foot": "right", "joinedOn": "2025-01-07", "signedFrom": "CA Osasuna Promesas", "contract": "2029-06-30", "marketValue": 1000000}, {"id": "634131", "name": "Aimar Oroz", "position": "Attacking Midfield", "dateOfBirth": "2001-11-27", "age": 24, "nationality": ["Spain"], "height": 177, "foot": "right", "joinedOn": "2022-01-07", "signedFrom": "CA Osasuna Promesas", "contract": "2029-06-30", "marketValue": 7500000}, {"id": "175449", "name": "Moi Gómez", "position": "Attacking Midfield", "dateOfBirth": "1994-06-23", "age": 31, "nationality": ["Spain"], "height": 176, "foot": "right", "joinedOn": "2022-07-28", "signedFrom": "Villarreal CF", "contract": "2027-06-30", "marketValue": 1500000}, {"id": "935231", "name": "Víctor Muñoz", "position": "Left Winger", "dateOfBirth": "2003-07-13", "age": 22, "nationality": ["Spain"], "height": 173, "foot": "right", "joinedOn": "2025-11-07", "signedFrom": "Real Madrid Castilla", "contract": "2030-06-30", "marketValue": 30000000}, {"id": "624942", "name": "Raúl Moro", "position": "Left Winger", "dateOfBirth": "2002-05-12", "age": 23, "nationality": ["Spain"], "height": 169, "foot": "right", "joinedOn": "2026-01-22", "signedFrom": "Ajax Amsterdam", "contract": "2031-06-30", "marketValue": 3500000}, {"id": "213260", "name": "Rubén García", "position": "Right Winger", "dateOfBirth": "1993-07-14", "age": 32, "nationality": ["Spain"], "height": 172, "foot": "left", "joinedOn": "2019-01-07", "signedFrom": "Levante UD", "contract": "2027-06-30", "marketValue": 1600000}, {"id": "298575", "name": "Kike Barja", "position": "Right Winger", "dateOfBirth": "1997-01-04", "age": 29, "nationality": ["Spain"], "height": 179, "foot": "right", "joinedOn": "2018-01-01", "signedFrom": "CA Osasuna Promesas", "contract": "2028-06-30", "marketValue": 1500000, "status": "Team captain"}, {"id": "710679", "name": "Iker Benito", "position": "Right Winger", "dateOfBirth": "2002-10-08", "age": 23, "nationality": ["Spain"], "height": 176, "foot": "right", "joinedOn": "2023-01-07", "signedFrom": "CA Osasuna Promesas", "contract": "2027-06-30", "marketValue": 1400000}, {"id": "631002", "name": "Raúl García", "position": "Centre-Forward", "dateOfBirth": "2000-03-11", "age": 25, "nationality": ["Spain"], "height": 192, "foot": "right", "joinedOn": "2023-10-08", "signedFrom": "Real Betis Balompié", "contract": "2031-06-30", "marketValue": 3000000}, {"id": "46413", "name": "Ante Budimir", "position": "Centre-Forward", "dateOfBirth": "1991-07-22", "age": 34, "nationality": ["Croatia"], "height": 190, "foot": "left", "joinedOn": "2021-01-07", "signedFrom": "RCD Mallorca", "contract": "2027-06-30", "marketValue": 2800000}]}