{"updatedAt": "2026-06-07T14:24:25.874513", "id": "6600", "players": [{"id": "869437", "name": "Anthoni", "position": "Goalkeeper", "dateOfBirth": "2002-01-23", "age": 24, "nationality": ["Brazil"], "height": 193, "foot": "right", "joinedOn": "2023-01-01", "signedFrom": "SC Internacional U20", "contract": "2029-12-31", "marketValue": 3000000}, {"id": "264014", "name": "Sergio Rochet", "position": "Goalkeeper", "dateOfBirth": "1993-03-23", "age": 33, "nationality": ["Uruguay", "Italy"], "height": 189, "foot": "right", "joinedOn": "2023-07-13", "signedFrom": "Club Nacional", "contract": "2026-12-31", "marketValue": 1800000, "status": "Called up to national team – cross-competition"}, {"id": "1094530", "name": "Kauan", "position": "Goalkeeper", "dateOfBirth": "2003-04-27", "age": 23, "nationality": ["Brazil"], "height": 192, "foot": "right", "joinedOn": "2024-01-07", "signedFrom": "SC Internacional U20", "contract": "2027-12-31"}, {"id": "1116612", "name": "Diego Esser", "position": "Goalkeeper", "dateOfBirth": "2005-04-13", "age": 21, "nationality": ["Brazil"], "height": 194, "foot": "left", "joinedOn": "2026-01-01", "signedFrom": "SC Internacional U20", "contract": "2026-12-31"}, {"id": "834444", "name": "Victor Gabriel", "position": "Centre-Back", "dateOfBirth": "2004-04-28", "age": 22, "nationality": ["Brazil"], "height": 187, "foot": "left", "joinedOn": "2026-01-01", "signedFrom": "Sport Recife U20", "contract": "2029-12-31", "marketValue": 5000000}, {"id": "468174", "name": "Félix Torres", "position": "Centre-Back", "dateOfBirth": "1997-11-01", "age": 29, "nationality": ["Ecuador"], "height": 187, "foot": "right", "joinedOn": "2026-01-18", "signedFrom": "Sport Club Corinthians Paulista", "contract": "2026-12-31", "marketValue": 1000000}, {"id": "383638", "name": "Juninho", "position": "Centre-Back", "dateOfBirth": "1995-01-02", "age": 31, "nationality": ["Brazil"], "height": 185, "foot": "left", "joinedOn": "2025-02-28", "signedFrom": "FC Midtjylland", "contract": "2027-12-31", "marketValue": 700000}, {"id": "371968", "name": "Clayton", "position": "Centre-Back", "dateOfBirth": "2000-04-04", "age": 26, "nationality": ["Brazil"], "height": 187, "foot": "right", "joinedOn": "2024-08-30", "signedFrom": "Avs Futebol", "contract": "2028-12-31", "marketValue": 700000}, {"id": "45319", "name": "Gabriel Mercado", "position": "Centre-Back", "dateOfBirth": "1987-03-18", "age": 39, "nationality": ["Argentina", "Spain"], "height": 180, "foot": "right", "joinedOn": "2021-05-07", "signedFrom": "Al-Rayyan SC", "contract": "2026-12-31", "marketValue": 100000}, {"id": "719635", "name": "Alexandro Bernabei", "position": "Left-Back", "dateOfBirth": "2000-09-24", "age": 25, "nationality": ["Argentina", "Italy"], "height": 169, "foot": "left", "joinedOn": "2025-09-01", "signedFrom": ": Ablöse €5.50m", "contract": "2028-12-31", "marketValue": 8000000}, {"id": "741021", "name": "Matheus Bahia", "position": "Left-Back", "dateOfBirth": "1999-11-08", "age": 26, "nationality": ["Brazil"], "height": 181, "foot": "left", "joinedOn": "2026-02-14", "signedFrom": "Esporte Clube Bahia", "contract": "2027-12-31", "marketValue": 3000000}, {"id": "703322", "name": "Bruno Gomes", "position": "Right-Back", "dateOfBirth": "2001-04-04", "age": 25, "nationality": ["Brazil", "Italy"], "height": 175, "foot": "right", "joinedOn": "2024-02-16", "signedFrom": "Coritiba Foot Ball Club", "contract": "2027-12-31", "marketValue": 6000000}, {"id": "829378", "name": "Braian Aguirre", "position": "Right-Back", "dateOfBirth": "2000-07-28", "age": 25, "nationality": ["Argentina"], "height": 175, "foot": "right", "joinedOn": "2024-02-09", "signedFrom": "CA Lanús", "contract": "2028-12-31", "marketValue": 2500000}, {"id": "657220", "name": "Rodrigo Villagra", "position": "Defensive Midfield", "dateOfBirth": "2001-02-14", "age": 25, "nationality": ["Argentina"], "height": 178, "foot": "right", "joinedOn": "2026-01-21", "signedFrom": "CSKA Moscow", "contract": "2026-12-31", "marketValue": 3500000}, {"id": "294873", "name": "Thiago Maia", "position": "Defensive Midfield", "dateOfBirth": "1997-03-23", "age": 29, "nationality": ["Brazil"], "height": 179, "foot": "left", "joinedOn": "2024-10-07", "signedFrom": "CR Flamengo", "contract": "2026-12-31", "marketValue": 2500000}, {"id": "405768", "name": "Ronaldo", "position": "Defensive Midfield", "dateOfBirth": "1996-10-23", "age": 29, "nationality": ["Brazil"], "height": 179, "foot": "right", "joinedOn": "2025-10-01", "signedFrom": "Esporte Clube Juventude", "contract": "2026-12-31", "marketValue": 2000000}, {"id": "530737", "name": "Richard", "position": "Defensive Midfield", "dateOfBirth": "1994-02-18", "age": 32, "nationality": ["Brazil"], "height": 191, "foot": "right", "joinedOn": "2025-07-17", "signedFrom": "Alanyaspor", "contract": "2026-12-31", "marketValue": 500000, "status": "Hip flexor problems - Return unknown"}, {"id": "1312046", "name": "Benjamin", "position": "Defensive Midfield", "dateOfBirth": "2006-05-29", "age": 20, "nationality": ["Ghana"], "height": 168, "foot": "right", "signedFrom": "", "contract": "2028-01-31"}, {"id": "465817", "name": "Alan Rodríguez", "position": "Central Midfield", "dateOfBirth": "2000-01-25", "age": 26, "nationality": ["Uruguay", "Italy"], "height": 174, "foot": "right", "joinedOn": "2025-07-30", "signedFrom": "AA Argentinos Juniors", "contract": "2029-12-31", "marketValue": 2300000, "status": "Leg injury - Return unknown"}, {"id": "534473", "name": "Paulinho Paula", "position": "Central Midfield", "dateOfBirth": "1997-08-01", "age": 29, "nationality": ["Brazil"], "height": 173, "foot": "right", "joinedOn": "2026-09-01", "signedFrom": "Clube de Regatas Vasco da Gama", "contract": "2027-12-31", "marketValue": 1000000}, {"id": "277335", "name": "Bruno Henrique", "position": "Central Midfield", "dateOfBirth": "1989-10-21", "age": 36, "nationality": ["Brazil", "Italy"], "height": 180, "foot": "right", "joinedOn": "2023-07-19", "signedFrom": "Al-Ittihad Club", "contract": "2026-12-31", "marketValue": 300000}, {"id": "104505", "name": "Alan Patrick", "position": "Attacking Midfield", "dateOfBirth": "1991-05-13", "age": 35, "nationality": ["Brazil"], "height": 177, "foot": "right", "joinedOn": "2022-11-04", "signedFrom": "Shakhtar Donetsk", "contract": "2027-12-31", "marketValue": 2000000, "status": "Team captain"}, {"id": "1220008", "name": "Allex", "position": "Attacking Midfield", "dateOfBirth": "2006-04-05", "age": 20, "nationality": ["Brazil"], "height": 164, "foot": "left", "joinedOn": "2026-01-18", "signedFrom": "SC Internacional U20", "contract": "2027-12-31", "marketValue": 1000000}, {"id": "1220010", "name": "Yago Noal", "position": "Attacking Midfield", "dateOfBirth": "2007-05-02", "age": 19, "nationality": ["Brazil"], "height": 171, "foot": "right", "signedFrom": "", "contract": "2028-12-31", "marketValue": 500000}, {"id": "572042", "name": "Johan Carbonero", "position": "Left Winger", "dateOfBirth": "1999-07-20", "age": 26, "nationality": ["Colombia"], "height": 170, "foot": "right", "joinedOn": "2026-01-01", "signedFrom": "Racing Club", "contract": "2029-12-31", "marketValue": 6000000}, {"id": "670965", "name": "Vitinho", "position": "Left Winger", "dateOfBirth": "1999-01-04", "age": 27, "nationality": ["Brazil"], "height": 180, "foot": "right", "joinedOn": "2025-10-01", "signedFrom": ": Ablöse -", "contract": "2026-06-30", "marketValue": 5000000}, {"id": "668265", "name": "Kayky", "position": "Right Winger", "dateOfBirth": "2003-11-06", "age": 22, "nationality": ["Brazil"], "height": 172, "foot": "left", "joinedOn": "2026-11-02", "signedFrom": "Esporte Clube Bahia", "contract": "2026-12-31", "marketValue": 5000000}, {"id": "438202", "name": "Bruno Tabata", "position": "Right Winger", "dateOfBirth": "1997-03-30", "age": 29, "nationality": ["Brazil"], "height": 175, "foot": "left", "joinedOn": "2024-11-08", "signedFrom": "Sociedade Esportiva Palmeiras", "contract": "2027-12-31", "marketValue": 1500000}, {"id": "323831", "name": "Rafael Borré", "position": "Centre-Forward", "dateOfBirth": "1995-09-15", "age": 30, "nationality": ["Colombia"], "height": 174, "foot": "right", "joinedOn": "2024-05-03", "signedFrom": "Eintracht Frankfurt", "contract": "2028-12-31", "marketValue": 3500000}, {"id": "371996", "name": "Alerrandro", "position": "Centre-Forward", "dateOfBirth": "2000-12-01", "age": 26, "nationality": ["Brazil"], "height": 181, "foot": "right", "joinedOn": "2026-01-30", "signedFrom": "CSKA Moscow", "contract": "2026-12-31", "marketValue": 3000000}, {"id": "1355429", "name": "Raykkonen", "position": "Centre-Forward", "dateOfBirth": "2008-07-13", "age": 17, "nationality": ["Brazil"], "height": 187, "foot": "right", "joinedOn": "2026-02-02", "signedFrom": "Goiás Esporte Clube U20", "contract": "2029-01-02", "marketValue": 1000000}]}