{"updatedAt": "2026-06-07T14:28:18.096817", "id": "667", "players": [{"id": "834397", "name": "Mike Penders", "position": "Goalkeeper", "dateOfBirth": "2005-07-31", "age": 20, "nationality": ["Belgium"], "height": 200, "foot": "left", "joinedOn": "2025-07-28", "signedFrom": "Chelsea FC", "contract": "2026-06-30", "marketValue": 25000000}, {"id": "465836", "name": "Stefan Bajic", "position": "Goalkeeper", "dateOfBirth": "2001-12-23", "age": 24, "nationality": ["France", "Serbia"], "height": 188, "foot": "right", "joinedOn": "2025-08-16", "signedFrom": "Bristol City", "contract": "2026-06-30", "marketValue": 300000}, {"id": "112822", "name": "Karl-Johan Johnsson", "position": "Goalkeeper", "dateOfBirth": "1990-01-28", "age": 36, "nationality": ["Sweden"], "height": 188, "foot": "right", "joinedOn": "2024-08-16", "signedFrom": "FC Girondins Bordeaux", "contract": "2026-06-30", "marketValue": 200000}, {"id": "786436", "name": "Ismaël Doukouré", "position": "Centre-Back", "dateOfBirth": "2003-07-24", "age": 22, "nationality": ["France", "Cote d'Ivoire"], "height": 183, "foot": "right", "joinedOn": "2022-01-29", "signedFrom": "Valenciennes FC", "contract": "2028-06-30", "marketValue": 20000000}, {"id": "926978", "name": "Lucas Høgsberg", "position": "Centre-Back", "dateOfBirth": "2006-06-23", "age": 19, "nationality": ["Denmark"], "height": 187, "foot": "right", "joinedOn": "2025-09-08", "signedFrom": "FC Nordsjaelland", "contract": "2030-06-30", "marketValue": 18000000}, {"id": "1145504", "name": "Aarón Anselmino", "position": "Centre-Back", "dateOfBirth": "2005-04-29", "age": 21, "nationality": ["Argentina"], "height": 186, "foot": "right", "joinedOn": "2026-02-02", "signedFrom": "Chelsea FC", "contract": "2026-06-30", "marketValue": 10000000}, {"id": "621993", "name": "Andrew Omobamidele", "position": "Centre-Back", "dateOfBirth": "2002-06-23", "age": 23, "nationality": ["Ireland", "Nigeria"], "height": 188, "foot": "right", "joinedOn": "2025-01-07", "signedFrom": "Nottingham Forest", "contract": "2029-06-30", "marketValue": 8000000, "status": "unknown injury - Return unknown"}, {"id": "316125", "name": "Ben Chilwell", "position": "Left-Back", "dateOfBirth": "1996-12-21", "age": 29, "nationality": ["England", "New Zealand"], "height": 180, "foot": "left", "joinedOn": "2025-01-09", "signedFrom": "Chelsea FC", "contract": "2027-06-30", "marketValue": 10000000}, {"id": "711980", "name": "Guéla Doué", "position": "Right-Back", "dateOfBirth": "2002-10-17", "age": 23, "nationality": ["Cote d'Ivoire", "France"], "height": 187, "foot": "right", "joinedOn": "2024-07-26", "signedFrom": "Stade Rennais FC", "contract": "2029-06-30", "marketValue": 20000000}, {"id": "991487", "name": "Abdoul Ouattara", "position": "Right-Back", "dateOfBirth": "2005-10-22", "age": 20, "nationality": ["Cote d'Ivoire", "France"], "height": 180, "foot": "", "joinedOn": "2025-01-01", "signedFrom": "Racing Strasbourg B", "contract": "2029-06-30", "marketValue": 15000000}, {"id": "1011200", "name": "Junior Mwanga", "position": "Defensive Midfield", "dateOfBirth": "2003-11-05", "age": 23, "nationality": ["France", "DR Congo"], "height": 184, "foot": "both", "joinedOn": "2023-08-08", "signedFrom": "FC Girondins Bordeaux", "contract": "2027-06-30", "marketValue": 6000000}, {"id": "863204", "name": "Maxi Oyedele", "position": "Defensive Midfield", "dateOfBirth": "2004-07-11", "age": 21, "nationality": ["Poland", "England"], "height": 183, "foot": "right", "joinedOn": "2025-07-16", "signedFrom": "Legia Warszawa", "contract": "2030-06-30", "marketValue": 5000000}, {"id": "637803", "name": "Rafael Luís", "position": "Defensive Midfield", "dateOfBirth": "2005-02-18", "age": 21, "nationality": ["Portugal"], "height": 188, "foot": "left", "joinedOn": "2025-08-17", "signedFrom": "SL Benfica B", "contract": "2026-06-30", "marketValue": 5000000}, {"id": "849410", "name": "Valentín Barco", "position": "Central Midfield", "dateOfBirth": "2004-07-23", "age": 21, "nationality": ["Argentina"], "height": 172, "foot": "left", "joinedOn": "2025-02-07", "signedFrom": "Brighton & Hove Albion", "contract": "2029-06-30", "marketValue": 40000000}, {"id": "1130514", "name": "Samir El Mourabet", "position": "Central Midfield", "dateOfBirth": "2005-06-10", "age": 20, "nationality": ["Morocco", "France"], "height": 187, "foot": "left", "joinedOn": "2025-01-07", "signedFrom": "Racing Strasbourg B", "contract": "2030-06-30", "marketValue": 22000000}, {"id": "1010854", "name": "Mathis Amougou", "position": "Central Midfield", "dateOfBirth": "2006-01-18", "age": 20, "nationality": ["France", "Cameroon"], "height": 177, "foot": "right", "joinedOn": "2025-12-07", "signedFrom": "Chelsea FC", "contract": "2030-06-30", "marketValue": 9000000}, {"id": "655006", "name": "Diego Moreira", "position": "Left Midfield", "dateOfBirth": "2004-06-08", "age": 21, "nationality": ["Belgium", "Portugal"], "height": 179, "foot": "left", "joinedOn": "2024-08-16", "signedFrom": "Chelsea FC", "contract": "2029-06-30", "marketValue": 25000000}, {"id": "579928", "name": "Sebastian Nanasi", "position": "Left Midfield", "dateOfBirth": "2002-05-16", "age": 24, "nationality": ["Sweden", "Hungary"], "height": 178, "foot": "right", "joinedOn": "2024-08-23", "signedFrom": "Malmö FF", "contract": "2029-06-30", "marketValue": 15000000}, {"id": "660867", "name": "Julio Enciso", "position": "Attacking Midfield", "dateOfBirth": "2004-01-23", "age": 22, "nationality": ["Paraguay"], "height": 168, "foot": "right", "joinedOn": "2025-01-09", "signedFrom": "Brighton & Hove Albion", "contract": "2029-06-30", "marketValue": 25000000}, {"id": "992686", "name": "Martial Godo", "position": "Left Winger", "dateOfBirth": "2003-03-14", "age": 23, "nationality": ["Cote d'Ivoire", "England"], "height": 177, "foot": "right", "joinedOn": "2025-01-09", "signedFrom": "Fulham FC", "contract": "2030-06-30", "marketValue": 22000000}, {"id": "1151929", "name": "Gessime Yassine", "position": "Right Winger", "dateOfBirth": "2005-11-22", "age": 20, "nationality": ["Morocco", "France"], "height": 172, "foot": "left", "joinedOn": "2026-01-17", "signedFrom": "USL Dunkerque", "contract": "2030-06-30", "marketValue": 12000000}, {"id": "933900", "name": "Samuel Amo-Ameyaw", "position": "Right Winger", "dateOfBirth": "2006-07-18", "age": 19, "nationality": ["England", "Ghana"], "height": 174, "foot": "left", "joinedOn": "2025-01-07", "signedFrom": "Southampton FC", "contract": "2029-06-30", "marketValue": 8000000}, {"id": "1133733", "name": "Yaya Diémé", "position": "Right Winger", "dateOfBirth": "2007-10-16", "age": 18, "nationality": ["Senegal"], "height": 180, "foot": "left", "signedFrom": "", "contract": "2030-06-30", "marketValue": 300000}, {"id": "1064871", "name": "Joaquín Panichelli", "position": "Centre-Forward", "dateOfBirth": "2002-07-10", "age": 23, "nationality": ["Argentina"], "height": 190, "foot": "right", "joinedOn": "2025-07-27", "signedFrom": "Deportivo Alavés", "contract": "2030-06-30", "marketValue": 35000000, "status": "Cruciate ligament tear - Return expected on 31/12/2026"}, {"id": "559328", "name": "Emmanuel Emegha", "position": "Centre-Forward", "dateOfBirth": "2003-03-02", "age": 23, "nationality": ["Netherlands", "Nigeria"], "height": 196, "foot": "right", "joinedOn": "2023-07-22", "signedFrom": "SK Sturm Graz", "contract": "2028-06-30", "marketValue": 25000000, "status": "Team captain; Dead leg - Return unknown"}, {"id": "787232", "name": "David Datro Fofana", "position": "Centre-Forward", "dateOfBirth": "2002-12-22", "age": 23, "nationality": ["Cote d'Ivoire"], "height": 182, "foot": "right", "joinedOn": "2026-02-02", "signedFrom": "Chelsea FC", "contract": "2026-06-30", "marketValue": 4000000}]}