{"updatedAt": "2026-06-07T14:26:27.928275", "id": "IT1", "name": "Serie A", "seasonId": "2025", "clubs": [{"id": "46", "name": "Inter Milan"}, {"id": "506", "name": "Juventus FC"}, {"id": "12", "name": "AS Roma"}, {"id": "5", "name": "AC Milan"}, {"id": "800", "name": "Atalanta BC"}, {"id": "6195", "name": "SSC Napoli"}, {"id": "1047", "name": "Como 1907"}, {"id": "1025", "name": "Bologna FC 1909"}, {"id": "430", "name": "ACF Fiorentina"}, {"id": "398", "name": "SS Lazio"}, {"id": "6574", "name": "US Sassuolo"}, {"id": "130", "name": "Parma Calcio 1913"}, {"id": "410", "name": "Udinese Calcio"}, {"id": "1390", "name": "Cagliari Calcio"}, {"id": "252", "name": "Genoa CFC"}, {"id": "416", "name": "Torino FC"}, {"id": "4172", "name": "Pisa Sporting Club"}, {"id": "1005", "name": "US Lecce"}, {"id": "276", "name": "Hellas Verona"}, {"id": "2239", "name": "US Cremonese"}]}